{"sections":{"breadcrumbs":{"type":"breadcrumbs","settings":{"border_top":false,"border_bottom":false,"use_background_transparent":false}},"main":{"type":"main-product","blocks":{"title":{"type":"title","settings":{"text_before":"{{ product.vendor }}","text_after":"","show_rating_judgeme":true,"show_sku":true,"show_price":true}},"gallery":{"type":"gallery","settings":{"show_navigation":false,"transition_effect":"fade_in","gallery_thumbs_mode":"grid_theme","thumbnail_size":320,"is_thumbnail_mobile_bullet":true,"show_badges":true,"badge_size":"md","use_gallery_placeholder":false,"placeholder_name":"product-1"}},"price":{"type":"price","settings":{"show_tax_message":false}},"description":{"type":"description","settings":{"is_collapsed":false,"initial_lines":3}},"variant_picker":{"type":"variant_picker","settings":{"picker_type":"button","mark_unavailable_variants":true,"show_swatch_colors":true}},"quantity_selector":{"type":"quantity_selector","settings":{}},"buy_buttons":{"type":"buy_buttons","settings":{"show_dynamic_checkout":true,"gift_card_show_recipient_form":true}},"pickup":{"type":"pickup","settings":{}},"collapsible_customer_service":{"type":"collapsible_tab","settings":{"heading":"Customer Service","content":"<p>Post your customer service details here.<\/p>","page":"","icon":"check_mark"}},"collapsible_return_policy":{"type":"collapsible_tab","settings":{"heading":"Return Policy","content":"<p>Post your policy conditions details here.<\/p>","page":"","icon":"return"}},"share":{"type":"share","settings":{"show_facebook":true,"show_twitter":true,"show_pinterest":true}}},"block_order":["title","gallery","price","description","variant_picker","quantity_selector","buy_buttons","pickup","collapsible_customer_service","collapsible_return_policy","share"],"settings":{"enable_sticky_info":false,"enable_quick_add":true,"animation_on_reveal":true,"center_product_info":false}},"product-tabs":{"type":"product-tabs","blocks":{"description":{"type":"description","settings":{"heading":"Description"}},"reviews":{"type":"reviews","settings":{"heading":"Reviews","enable_theme_appearance":true}},"faq":{"type":"faq","settings":{"heading":"Frequently Asked Questions","default_faqs":"What level of performance can I expect from 4K Color Drive?:This tv comes equipped with a 4k color drive, which allows the tv to accurately reproduce a wider spectrum of colors. you’ll experience an exceptionally vibrant, pristine image that makes each scene more lifelike.","link_to_faq_page":""}},"similar":{"type":"similar","disabled":true,"settings":{"heading":"Similar Products","source":[],"is_random":true,"products_per_page":4,"badge_size":"sm","image_ratio":"settings|product_card_image_ratio","show_to_cart_button":false}}},"block_order":["description","reviews","faq","similar"],"settings":{"tabs_layout":"collapsed","collapsed_tabs_color":"#000000","collapsed_tabs_bg":"","collapsed_tabs_bg_gradient":"linear-gradient(to left, #A0E8FE 0%, #FCE0FC 100%)","section_tabs_bg":"#f6f5f4","section_tabs_bg_gradient":"","animation_on_reveal":true}},"products-recommendations":{"type":"product-recommendations","settings":{"title":"You may also like","heading_size":"h2","products_to_show":8,"products_per_row":4,"products_background_color":"#ffffff","products_appearance":"slider","show_slider_buttons":true,"animation_on_reveal":true,"badge_size":"md","image_ratio":"settings|product_card_image_ratio","show_to_cart_button":true}},"products-complementary":{"type":"product-complementary","settings":{"title":"Complementary products","heading_size":"h2","products_to_show":8,"products_per_row":4,"products_background_color":"#ffffff","products_appearance":"slider","show_slider_buttons":true,"animation_on_reveal":true,"badge_size":"md","image_ratio":"settings|product_card_image_ratio","show_to_cart_button":true}},"border_separator_1":{"type":"border-separator","settings":{"border_height":1,"border_color":""}},"recent_posts":{"type":"featured-blog","settings":{"heading":"Recent stories","blog":"news","post_limit":3,"animation_on_reveal":true,"show_image":true,"tags_limit":3,"excerpt_limit":0,"show_date":true,"show_link":false,"show_comments":false}},"border_separator_2":{"type":"border-separator","settings":{"border_height":1,"border_color":""}}},"order":["breadcrumbs","main","product-tabs","products-recommendations","products-complementary","border_separator_1","recent_posts","border_separator_2"]}